tests/__init__.py
tests/test_biff_records.py
tests/test_bitmaps.py
tests/test_by_name_functions.py
tests/test_compound_doc.py
tests/test_easyxf.py
tests/test_mini.py
tests/test_simple.py
tests/test_unicode1.py
tests/test_unicodeutils.py
tests/test_worksheet.py
tests/utils.py
xlwt/BIFFRecords.py
xlwt/Bitmap.py
xlwt/Cell.py
xlwt/Column.py
xlwt/CompoundDoc.py
xlwt/ExcelFormula.py
xlwt/ExcelFormulaLexer.py
xlwt/ExcelFormulaParser.py
xlwt/ExcelMagic.py
xlwt/Formatting.py
xlwt/Row.py
xlwt/Style.py
xlwt/UnicodeUtils.py
xlwt/Utils.py
xlwt/Workbook.py
xlwt/Worksheet.py
xlwt/__init__.py
xlwt/antlr.py
xlwt/compat.py
xlwt_fix-1.3.1.dist-info/LICENSE
xlwt_fix-1.3.1.dist-info/METADATA
xlwt_fix-1.3.1.dist-info/WHEEL
xlwt_fix-1.3.1.dist-info/top_level.txt
xlwt_fix-1.3.1.dist-info/RECORD
